{
  "Workflows": [
    {
      "Path": null,
      "SortBy": 0,
      "VariablesSectionElementsOrder": [],
      "ArgumentsSectionElementsOrder": null,
      "ConstantsSectionElementsOrder": [],
      "AddedNamespaces": null
    },
    {
      "Path": "Main.xaml",
      "SortBy": 0,
      "VariablesSectionElementsOrder": [
        "StrTo&Sequence_1",
        "StrCc&Sequence_1",
        "receiptent&Sequence_1",
        "cc&Sequence_3",
        "IDlist&Sequence_2"
      ],
      "ArgumentsSectionElementsOrder": [],
      "ConstantsSectionElementsOrder": [],
      "AddedNamespaces": null
    },
    {
      "Path": "../../../Desktop/Send E-mail.xaml",
      "SortBy": 0,
      "VariablesSectionElementsOrder": [
        "receiptent&Sequence_1",
        "StrTo&Sequence_1",
        "StrCc&Sequence_1",
        "IDlist&Sequence_2",
        "cc&Sequence_3"
      ],
      "ArgumentsSectionElementsOrder": [],
      "ConstantsSectionElementsOrder": [],
      "AddedNamespaces": null
    },
    {
      "Path": "../../../Desktop/1.xaml",
      "SortBy": 0,
      "VariablesSectionElementsOrder": [
        "strTo&Sequence_14",
        "cc&Sequence_1",
        "IDlist&Sequence_1",
        "StrTo&Sequence_1",
        "StrCc&Sequence_1"
      ],
      "ArgumentsSectionElementsOrder": [],
      "ConstantsSectionElementsOrder": [],
      "AddedNamespaces": null
    }
  ]
}